Workbook

Sheet RAW_DATA
A1: Date | B1: Month | C1: Year | D1: Type | E1: Category | F1: Sub-Category | G1: Description | H1: Amount | I1: Account | J1: Notes
A2: 2023-01-01 | B2: Jan | C2: 2023 | D2: Income | E2: Salary | F2: Monthly Salary | G2: Monthly Salary Credit | H2: 65000 | I2: HDFC Savings
A3: 2023-01-10 | B3: Jan | C3: 2023 | D3: Income | E3: Freelance | F3: Project Payment | G3: Freelance Project | H3: 5409 | I3: HDFC Savings
A4: 2023-01-07 | B4: Jan | C4: 2023 | D4: Savings | E4: Investments | F4: Mutual Fund SIP | G4: Zerodha SIP - Nifty 50 | H4: 10000 | I4: Zerodha
A5: 2023-01-06 | B5: Jan | C5: 2023 | D5: Expense | E5: Housing | F5: Electricity | G5: Electricity - Jan 2023 | H5: 9657 | I5: HDFC Savings
A6: 2023-01-15 | B6: Jan | C6: 2023 | D6: Expense | E6: Food | F6: Groceries | G6: Groceries - Jan 2023 | H6: 4518 | I6: HDFC Savings
A7: 2023-01-24 | B7: Jan | C7: 2023 | D7: Expense | E7: Shopping | F7: Clothing | G7: Clothing - Jan 2023 | H7: 2314 | I7: Zerodha
A8: 2023-01-10 | B8: Jan | C8: 2023 | D8: Expense | E8: Entertainment | F8: Games | G8: Games - Jan 2023 | H8: 1143 | I8: HDFC Savings
A9: 2023-01-15 | B9: Jan | C9: 2023 | D9: Expense | E9: Education | F9: Books | G9: Books - Jan 2023 | H9: 2629 | I9: ICICI CC
A10: 2023-02-01 | B10: Feb | C10: 2023 | D10: Income | E10: Salary | F10: Monthly Salary | G10: Monthly Salary Credit | H10: 65000 | I10: HDFC Savings
A11: 2023-02-07 | B11: Feb | C11: 2023 | D11: Savings | E11: Investments | F11: Mutual Fund SIP | G11: Zerodha SIP - Nifty 50 | H11: 10000 | I11: Zerodha
A12: 2023-02-14 | B12: Feb | C12: 2023 | D12: Expense | E12: Housing | F12: Rent | G12: Rent - Feb 2023 | H12: 7519 | I12: HDFC Savings
A13: 2023-02-10 | B13: Feb | C13: 2023 | D13: Expense | E13: Food | F13: Coffee | G13: Coffee - Feb 2023 | H13: 4572 | I13: HDFC Savings
... A200: 2024-12-13 | B200: Dec | C200: 2024 | D200: Expense | E200: Shopping | F200: Personal Care | G200: Personal Care - Dec 2024 | H200: 2854 | I200: Cash

Sheet MONTHLY_SUMMARY
A1: 📊 MONTHLY INCOME & EXPENSE SUMMARY
A2: Year | B2: Month | C2: Total Income | D2: Total Expense | E2: Total Savings | F2: Net Cash Flow | G2: Savings Rate % | H2: Housing | I2: Food | J2: Transport | K2: Health | L2: Shopping | M2: Entertainment | N2: Education | O2: Others | P2: Cumulative Savings
A3: 2023 | B3: Jan | C3: =SUMPRODUCT((RAW_DATA!B$2:B$5000=B3)*(RAW_DATA!C$2:C$5000=A3)*(RAW_DATA!D$2:D$5000="Income")*RAW_DATA!H$2:H$5000) -> 70409 | D3: =SUMPRODUCT((RAW_DATA!B$2:B$5000=B3)*(RAW_DATA!C$2:C$5000=A3)*(RAW_DATA!D$2:D$5000="Expense")*RAW_DATA!H$2:H$5000) -> 20261 | E3: =SUMPRODUCT((RAW_DATA!B$2:B$5000=B3)*(RAW_DATA!C$2:C$5000=A3)*(RAW_DATA!D$2:D$5000="Savings")*RAW_DATA!H$2:H$5000) -> 10000 | F3: =C3-D3-E3 -> 40148 | G3: =IF(C3>0,(E3+F3)/C3,0) -> 0.71223849 | H3: =SUMPRODUCT((RAW_DATA!B$2:B$5000=B3)*(RAW_DATA!C$2:C$5000=A3)*(RAW_DATA!E$2:E$5000="Housing")*RAW_DATA!H$2:H$5000) -> 9657 | I3: =SUMPRODUCT((RAW_DATA!B$2:B$5000=B3)*(RAW_DATA!C$2:C$5000=A3)*(RAW_DATA!E$2:E$5000="Food")*RAW_DATA!H$2:H$5000) -> 4518 | J3: =SUMPRODUCT((RAW_DATA!B$2:B$5000=B3)*(RAW_DATA!C$2:C$5000=A3)*(RAW_DATA!E$2:E$5000="Transport")*RAW_DATA!H$2:H$5000) -> 0 | K3: =SUMPRODUCT((RAW_DATA!B$2:B$5000=B3)*(RAW_DATA!C$2:C$5000=A3)*(RAW_DATA!E$2:E$5000="Health")*RAW_DATA!H$2:H$5000) -> 0 | L3: =SUMPRODUCT((RAW_DATA!B$2:B$5000=B3)*(RAW_DATA!C$2:C$5000=A3)*(RAW_DATA!E$2:E$5000="Shopping")*RAW_DATA!H$2:H$5000) -> 2314 | M3: =SUMPRODUCT((RAW_DATA!B$2:B$5000=B3)*(RAW_DATA!C$2:C$5000=A3)*(RAW_DATA!E$2:E$5000="Entertainment")*RAW_DATA!H$2:H$5000) -> 1143 | N3: =SUMPRODUCT((RAW_DATA!B$2:B$5000=B3)*(RAW_DATA!C$2:C$5000=A3)*(RAW_DATA!E$2:E$5000="Education")*RAW_DATA!H$2:H$5000) -> 2629 | O3: =SUMPRODUCT((RAW_DATA!B$2:B$5000=B3)*(RAW_DATA!C$2:C$5000=A3)*(RAW_DATA!E$2:E$5000="Others")*RAW_DATA!H$2:H$5000) -> 0 | P3: =E3+F3 -> 50148
A4: 2023 | B4: Feb | C4: =SUMPRODUCT((RAW_DATA!B$2:B$5000=B4)*(RAW_DATA!C$2:C$5000=A4)*(RAW_DATA!D$2:D$5000="Income")*RAW_DATA!H$2:H$5000) -> 65000 | D4: =SUMPRODUCT((RAW_DATA!B$2:B$5000=B4)*(RAW_DATA!C$2:C$5000=A4)*(RAW_DATA!D$2:D$5000="Expense")*RAW_DATA!H$2:H$5000) -> 16053 | E4: =SUMPRODUCT((RAW_DATA!B$2:B$5000=B4)*(RAW_DATA!C$2:C$5000=A4)*(RAW_DATA!D$2:D$5000="Savings")*RAW_DATA!H$2:H$5000) -> 10000 | F4: =C4-D4-E4 -> 38947 | G4: =IF(C4>0,(E4+F4)/C4,0) -> 0.75303077 | H4: =SUMPRODUCT((RAW_DATA!B$2:B$5000=B4)*(RAW_DATA!C$2:C$5000=A4)*(RAW_DATA!E$2:E$5000="Housing")*RAW_DATA!H$2:H$5000) -> 7519 | I4: =SUMPRODUCT((RAW_DATA!B$2:B$5000=B4)*(RAW_DATA!C$2:C$5000=A4)*(RAW_DATA!E$2:E$5000="Food")*RAW_DATA!H$2:H$5000) -> 4572 | J4: =SUMPRODUCT((RAW_DATA!B$2:B$5000=B4)*(RAW_DATA!C$2:C$5000=A4)*(RAW_DATA!E$2:E$5000="Transport")*RAW_DATA!H$2:H$5000) -> 1675 | K4: =SUMPRODUCT((RAW_DATA!B$2:B$5000=B4)*(RAW_DATA!C$2:C$5000=A4)*(RAW_DATA!E$2:E$5000="Health")*RAW_DATA!H$2:H$5000) -> 0 | L4: =SUMPRODUCT((RAW_DATA!B$2:B$5000=B4)*(RAW_DATA!C$2:C$5000=A4)*(RAW_DATA!E$2:E$5000="Shopping")*RAW_DATA!H$2:H$5000) -> 2287 | M4: =SUMPRODUCT((RAW_DATA!B$2:B$5000=B4)*(RAW_DATA!C$2:C$5000=A4)*(RAW_DATA!E$2:E$5000="Entertainment")*RAW_DATA!H$2:H$5000) -> 0 | N4: =SUMPRODUCT((RAW_DATA!B$2:B$5000=B4)*(RAW_DATA!C$2:C$5000=A4)*(RAW_DATA!E$2:E$5000="Education")*RAW_DATA!H$2:H$5000) -> 0 | O4: =SUMPRODUCT((RAW_DATA!B$2:B$5000=B4)*(RAW_DATA!C$2:C$5000=A4)*(RAW_DATA!E$2:E$5000="Others")*RAW_DATA!H$2:H$5000) -> 0 | P4: =P3+E4+F4 -> 99095
A5: 2023 | B5: Mar | C5: =SUMPRODUCT((RAW_DATA!B$2:B$5000=B5)*(RAW_DATA!C$2:C$5000=A5)*(RAW_DATA!D$2:D$5000="Income")*RAW_DATA!H$2:H$5000) -> 82961 | D5: =SUMPRODUCT((RAW_DATA!B$2:B$5000=B5)*(RAW_DATA!C$2:C$5000=A5)*(RAW_DATA!D$2:D$5000="Expense")*RAW_DATA!H$2:H$5000) -> 21772 | E5: =SUMPRODUCT((RAW_DATA!B$2:B$5000=B5)*(RAW_DATA!C$2:C$5000=A5)*(RAW_DATA!D$2:D$5000="Savings")*RAW_DATA!H$2:H$5000) -> 15000 | F5: =C5-D5-E5 -> 46189 | G5: =IF(C5>0,(E5+F5)/C5,0) -> 0.73756343 | H5: =SUMPRODUCT((RAW_DATA!B$2:B$5000=B5)*(RAW_DATA!C$2:C$5000=A5)*(RAW_DATA!E$2:E$5000="Housing")*RAW_DATA!H$2:H$5000) -> 11977 | I5: =SUMPRODUCT((RAW_DATA!B$2:B$5000=B5)*(RAW_DATA!C$2:C$5000=A5)*(RAW_DATA!E$2:E$5000="Food")*RAW_DATA!H$2:H$5000) -> 4974 | J5: =SUMPRODUCT((RAW_DATA!B$2:B$5000=B5)*(RAW_DATA!C$2:C$5000=A5)*(RAW_DATA!E$2:E$5000="Transport")*RAW_DATA!H$2:H$5000) -> 1993 | K5: =SUMPRODUCT((RAW_DATA!B$2:B$5000=B5)*(RAW_DATA!C$2:C$5000=A5)*(RAW_DATA!E$2:E$5000="Health")*RAW_DATA!H$2:H$5000) -> 0 | L5: =SUMPRODUCT((RAW_DATA!B$2:B$5000=B5)*(RAW_DATA!C$2:C$5000=A5)*(RAW_DATA!E$2:E$5000="Shopping")*RAW_DATA!H$2:H$5000) -> 2828 | M5: =SUMPRODUCT((RAW_DATA!B$2:B$5000=B5)*(RAW_DATA!C$2:C$5000=A5)*(RAW_DATA!E$2:E$5000="Entertainment")*RAW_DATA!H$2:H$5000) -> 0 | N5: =SUMPRODUCT((RAW_DATA!B$2:B$5000=B5)*(RAW_DATA!C$2:C$5000=A5)*(RAW_DATA!E$2:E$5000="Education")*RAW_DATA!H$2:H$5000) -> 0 | O5: =SUMPRODUCT((RAW_DATA!B$2:B$5000=B5)*(RAW_DATA!C$2:C$5000=A5)*(RAW_DATA!E$2:E$5000="Others")*RAW_DATA!H$2:H$5000) -> 0 | P5: =P4+E5+F5 -> 160284
A6: 2023 | B6: Apr | C6: =SUMPRODUCT((RAW_DATA!B$2:B$5000=B6)*(RAW_DATA!C$2:C$5000=A6)*(RAW_DATA!D$2:D$5000="Income")*RAW_DATA!H$2:H$5000) -> 65000 | D6: =SUMPRODUCT((RAW_DATA!B$2:B$5000=B6)*(RAW_DATA!C$2:C$5000=A6)*(RAW_DATA!D$2:D$5000="Expense")*RAW_DATA!H$2:H$5000) -> 11080 | E6: =SUMPRODUCT((RAW_DATA!B$2:B$5000=B6)*(RAW_DATA!C$2:C$5000=A6)*(RAW_DATA!D$2:D$5000="Savings")*RAW_DATA!H$2:H$5000) -> 10000 | F6: =C6-D6-E6 -> 43920 | G6: =IF(C6>0,(E6+F6)/C6,0) -> 0.82953846 | H6: =SUMPRODUCT((RAW_DATA!B$2:B$5000=B6)*(RAW_DATA!C$2:C$5000=A6)*(RAW_DATA!E$2:E$5000="Housing")*RAW_DATA!H$2:H$5000) -> 0 | I6: =SUMPRODUCT((RAW_DATA!B$2:B$5000=B6)*(RAW_DATA!C$2:C$5000=A6)*(RAW_DATA!E$2:E$5000="Food")*RAW_DATA!H$2:H$5000) -> 2970 | J6: =SUMPRODUCT((RAW_DATA!B$2:B$5000=B6)*(RAW_DATA!C$2:C$5000=A6)*(RAW_DATA!E$2:E$5000="Transport")*RAW_DATA!H$2:H$5000) -> 1192 | K6: =SUMPRODUCT((RAW_DATA!B$2:B$5000=B6)*(RAW_DATA!C$2:C$5000=A6)*(RAW_DATA!E$2:E$5000="Health")*RAW_DATA!H$2:H$5000) -> 0 | L6: =SUMPRODUCT((RAW_DATA!B$2:B$5000=B6)*(RAW_DATA!C$2:C$5000=A6)*(RAW_DATA!E$2:E$5000="Shopping")*RAW_DATA!H$2:H$5000) -> 3254 | M6: =SUMPRODUCT((RAW_DATA!B$2:B$5000=B6)*(RAW_DATA!C$2:C$5000=A6)*(RAW_DATA!E$2:E$5000="Entertainment")*RAW_DATA!H$2:H$5000) -> 1061 | N6: =SUMPRODUCT((RAW_DATA!B$2:B$5000=B6)*(RAW_DATA!C$2:C$5000=A6)*(RAW_DATA!E$2:E$5000="Education")*RAW_DATA!H$2:H$5000) -> 1513 | O6: =SUMPRODUCT((RAW_DATA!B$2:B$5000=B6)*(RAW_DATA!C$2:C$5000=A6)*(RAW_DATA!E$2:E$5000="Others")*RAW_DATA!H$2:H$5000) -> 1090 | P6: =P5+E6+F6 -> 214204
A7: 2023 | B7: May | C7: =SUMPRODUCT((RAW_DATA!B$2:B$5000=B7)*(RAW_DATA!C$2:C$5000=A7)*(RAW_DATA!D$2:D$5000="Income")*RAW_DATA!H$2:H$5000) -> 65000 | D7: =SUMPRODUCT((RAW_DATA!B$2:B$5000=B7)*(RAW_DATA!C$2:C$5000=A7)*(RAW_DATA!D$2:D$5000="Expense")*RAW_DATA!H$2:H$5000) -> 20809 | E7: =SUMPRODUCT((RAW_DATA!B$2:B$5000=B7)*(RAW_DATA!C$2:C$5000=A7)*(RAW_DATA!D$2:D$5000="Savings")*RAW_DATA!H$2:H$5000) -> 10000 | F7: =C7-D7-E7 -> 34191 | G7: =IF(C7>0,(E7+F7)/C7,0) -> 0.67986154 | H7: =SUMPRODUCT((RAW_DATA!B$2:B$5000=B7)*(RAW_DATA!C$2:C$5000=A7)*(RAW_DATA!E$2:E$5000="Housing")*RAW_DATA!H$2:H$5000) -> 10119 | I7: =SUMPRODUCT((RAW_DATA!B$2:B$5000=B7)*(RAW_DATA!C$2:C$5000=A7)*(RAW_DATA!E$2:E$5000="Food")*RAW_DATA!H$2:H$5000) -> 4892 | J7: =SUMPRODUCT((RAW_DATA!B$2:B$5000=B7)*(RAW_DATA!C$2:C$5000=A7)*(RAW_DATA!E$2:E$5000="Transport")*RAW_DATA!H$2:H$5000) -> 1128 | K7: =SUMPRODUCT((RAW_DATA!B$2:B$5000=B7)*(RAW_DATA!C$2:C$5000=A7)*(RAW_DATA!E$2:E$5000="Health")*RAW_DATA!H$2:H$5000) -> 0 | L7: =SUMPRODUCT((RAW_DATA!B$2:B$5000=B7)*(RAW_DATA!C$2:C$5000=A7)*(RAW_DATA!E$2:E$5000="Shopping")*RAW_DATA!H$2:H$5000) -> 0 | M7: =SUMPRODUCT((RAW_DATA!B$2:B$5000=B7)*(RAW_DATA!C$2:C$5000=A7)*(RAW_DATA!E$2:E$5000="Entertainment")*RAW_DATA!H$2:H$5000) -> 1052 | N7: =SUMPRODUCT((RAW_DATA!B$2:B$5000=B7)*(RAW_DATA!C$2:C$5000=A7)*(RAW_DATA!E$2:E$5000="Education")*RAW_DATA!H$2:H$5000) -> 2982 | O7: =SUMPRODUCT((RAW_DATA!B$2:B$5000=B7)*(RAW_DATA!C$2:C$5000=A7)*(RAW_DATA!E$2:E$5000="Others")*RAW_DATA!H$2:H$5000) -> 636 | P7: =P6+E7+F7 -> 258395
A8: 2023 | B8: Jun | C8: =SUMPRODUCT((RAW_DATA!B$2:B$5000=B8)*(RAW_DATA!C$2:C$5000=A8)*(RAW_DATA!D$2:D$5000="Income")*RAW_DATA!H$2:H$5000) -> 65000 | D8: =SUMPRODUCT((RAW_DATA!B$2:B$5000=B8)*(RAW_DATA!C$2:C$5000=A8)*(RAW_DATA!D$2:D$5000="Expense")*RAW_DATA!H$2:H$5000) -> 14890 | E8: =SUMPRODUCT((RAW_DATA!B$2:B$5000=B8)*(RAW_DATA!C$2:C$5000=A8)*(RAW_DATA!D$2:D$5000="Savings")*RAW_DATA!H$2:H$5000) -> 15000 | F8: =C8-D8-E8 -> 35110 | G8: =IF(C8>0,(E8+F8)/C8,0) -> 0.77092308 | H8: =SUMPRODUCT((RAW_DATA!B$2:B$5000=B8)*(RAW_DATA!C$2:C$5000=A8)*(RAW_DATA!E$2:E$5000="Housing")*RAW_DATA!H$2:H$5000) -> 6009 | I8: =SUMPRODUCT((RAW_DATA!B$2:B$5000=B8)*(RAW_DATA!C$2:C$5000=A8)*(RAW_DATA!E$2:E$5000="Food")*RAW_DATA!H$2:H$5000) -> 3586 | J8: =SUMPRODUCT((RAW_DATA!B$2:B$5000=B8)*(RAW_DATA!C$2:C$5000=A8)*(RAW_DATA!E$2:E$5000="Transport")*RAW_DATA!H$2:H$5000) -> 0 | K8: =SUMPRODUCT((RAW_DATA!B$2:B$5000=B8)*(RAW_DATA!C$2:C$5000=A8)*(RAW_DATA!E$2:E$5000="Health")*RAW_DATA!H$2:H$5000) -> 0 | L8: =SUMPRODUCT((RAW_DATA!B$2:B$5000=B8)*(RAW_DATA!C$2:C$5000=A8)*(RAW_DATA!E$2:E$5000="Shopping")*RAW_DATA!H$2:H$5000) -> 1850 | M8: =SUMPRODUCT((RAW_DATA!B$2:B$5000=B8)*(RAW_DATA!C$2:C$5000=A8)*(RAW_DATA!E$2:E$5000="Entertainment")*RAW_DATA!H$2:H$5000) -> 671 | N8: =SUMPRODUCT((RAW_DATA!B$2:B$5000=B8)*(RAW_DATA!C$2:C$5000=A8)*(RAW_DATA!E$2:E$5000="Education")*RAW_DATA!H$2:H$5000) -> 1742 | O8: =SUMPRODUCT((RAW_DATA!B$2:B$5000=B8)*(RAW_DATA!C$2:C$5000=A8)*(RAW_DATA!E$2:E$5000="Others")*RAW_DATA!H$2:H$5000) -> 1032 | P8: =P7+E8+F8 -> 308505
A9: 2023 | B9: Jul | C9: =SUMPRODUCT((RAW_DATA!B$2:B$5000=B9)*(RAW_DATA!C$2:C$5000=A9)*(RAW_DATA!D$2:D$5000="Income")*RAW_DATA!H$2:H$5000) -> 76537 | D9: =SUMPRODUCT((RAW_DATA!B$2:B$5000=B9)*(RAW_DATA!C$2:C$5000=A9)*(RAW_DATA!D$2:D$5000="Expense")*RAW_DATA!H$2:H$5000) -> 19637 | E9: =SUMPRODUCT((RAW_DATA!B$2:B$5000=B9)*(RAW_DATA!C$2:C$5000=A9)*(RAW_DATA!D$2:D$5000="Savings")*RAW_DATA!H$2:H$5000) -> 10000 | F9: =C9-D9-E9 -> 46900 | G9: =IF(C9>0,(E9+F9)/C9,0) -> 0.74343128 | H9: =SUMPRODUCT((RAW_DATA!B$2:B$5000=B9)*(RAW_DATA!C$2:C$5000=A9)*(RAW_DATA!E$2:E$5000="Housing")*RAW_DATA!H$2:H$5000) -> 13177 | I9: =SUMPRODUCT((RAW_DATA!B$2:B$5000=B9)*(RAW_DATA!C$2:C$5000=A9)*(RAW_DATA!E$2:E$5000="Food")*RAW_DATA!H$2:H$5000) -> 0 | J9: =SUMPRODUCT((RAW_DATA!B$2:B$5000=B9)*(RAW_DATA!C$2:C$5000=A9)*(RAW_DATA!E$2:E$5000="Transport")*RAW_DATA!H$2:H$5000) -> 0 | K9: =SUMPRODUCT((RAW_DATA!B$2:B$5000=B9)*(RAW_DATA!C$2:C$5000=A9)*(RAW_DATA!E$2:E$5000="Health")*RAW_DATA!H$2:H$5000) -> 0 | L9: =SUMPRODUCT((RAW_DATA!B$2:B$5000=B9)*(RAW_DATA!C$2:C$5000=A9)*(RAW_DATA!E$2:E$5000="Shopping")*RAW_DATA!H$2:H$5000) -> 2402 | M9: =SUMPRODUCT((RAW_DATA!B$2:B$5000=B9)*(RAW_DATA!C$2:C$5000=A9)*(RAW_DATA!E$2:E$5000="Entertainment")*RAW_DATA!H$2:H$5000) -> 774 | N9: =SUMPRODUCT((RAW_DATA!B$2:B$5000=B9)*(RAW_DATA!C$2:C$5000=A9)*(RAW_DATA!E$2:E$5000="Education")*RAW_DATA!H$2:H$5000) -> 2252 | O9: =SUMPRODUCT((RAW_DATA!B$2:B$5000=B9)*(RAW_DATA!C$2:C$5000=A9)*(RAW_DATA!E$2:E$5000="Others")*RAW_DATA!H$2:H$5000) -> 1032 | P9: =P8+E9+F9 -> 365405
A10: 2023 | B10: Aug | C10: =SUMPRODUCT((RAW_DATA!B$2:B$5000=B10)*(RAW_DATA!C$2:C$5000=A10)*(RAW_DATA!D$2:D$5000="Income")*RAW_DATA!H$2:H$5000) -> 73981 | D10: =SUMPRODUCT((RAW_DATA!B$2:B$5000=B10)*(RAW_DATA!C$2:C$5000=A10)*(RAW_DATA!D$2:D$5000="Expense")*RAW_DATA!H$2:H$5000) -> 20788 | E10: =SUMPRODUCT((RAW_DATA!B$2:B$5000=B10)*(RAW_DATA!C$2:C$5000=A10)*(RAW_DATA!D$2:D$5000="Savings")*RAW_DATA!H$2:H$5000) -> 10000 | F10: =C10-D10-E10 -> 43193 | G10: =IF(C10>0,(E10+F10)/C10,0) -> 0.71900893 | H10: =SUMPRODUCT((RAW_DATA!B$2:B$5000=B10)*(RAW_DATA!C$2:C$5000=A10)*(RAW_DATA!E$2:E$5000="Housing")*RAW_DATA!H$2:H$5000) -> 9119 | I10: =SUMPRODUCT((RAW_DATA!B$2:B$5000=B10)*(RAW_DATA!C$2:C$5000=A10)*(RAW_DATA!E$2:E$5000="Food")*RAW_DATA!H$2:H$5000) -> 3834 | J10: =SUMPRODUCT((RAW_DATA!B$2:B$5000=B10)*(RAW_DATA!C$2:C$5000=A10)*(RAW_DATA!E$2:E$5000="Transport")*RAW_DATA!H$2:H$5000) -> 2238 | K10: =SUMPRODUCT((RAW_DATA!B$2:B$5000=B10)*(RAW_DATA!C$2:C$5000=A10)*(RAW_DATA!E$2:E$5000="Health")*RAW_DATA!H$2:H$5000) -> 0 | L10: =SUMPRODUCT((RAW_DATA!B$2:B$5000=B10)*(RAW_DATA!C$2:C$5000=A10)*(RAW_DATA!E$2:E$5000="Shopping")*RAW_DATA!H$2:H$5000) -> 2518 | M10: =SUMPRODUCT((RAW_DATA!B$2:B$5000=B10)*(RAW_DATA!C$2:C$5000=A10)*(RAW_DATA!E$2:E$5000="Entertainment")*RAW_DATA!H$2:H$5000) -> 972 | N10: =SUMPRODUCT((RAW_DATA!B$2:B$5000=B10)*(RAW_DATA!C$2:C$5000=A10)*(RAW_DATA!E$2:E$5000="Education")*RAW_DATA!H$2:H$5000) -> 2107 | O10: =SUMPRODUCT((RAW_DATA!B$2:B$5000=B10)*(RAW_DATA!C$2:C$5000=A10)*(RAW_DATA!E$2:E$5000="Others")*RAW_DATA!H$2:H$5000) -> 0 | P10: =P9+E10+F10 -> 418598
A11: 2023 | B11: Sep | C11: =SUMPRODUCT((RAW_DATA!B$2:B$5000=B11)*(RAW_DATA!C$2:C$5000=A11)*(RAW_DATA!D$2:D$5000="Income")*RAW_DATA!H$2:H$5000) -> 90384 | D11: =SUMPRODUCT((RAW_DATA!B$2:B$5000=B11)*(RAW_DATA!C$2:C$5000=A11)*(RAW_DATA!D$2:D$5000="Expense")*RAW_DATA!H$2:H$5000) -> 15303 | E11: =SUMPRODUCT((RAW_DATA!B$2:B$5000=B11)*(RAW_DATA!C$2:C$5000=A11)*(RAW_DATA!D$2:D$5000="Savings")*RAW_DATA!H$2:H$5000) -> 15000 | F11: =C11-D11-E11 -> 60081 | G11: =IF(C11>0,(E11+F11)/C11,0) -> 0.83068906 | H11: =SUMPRODUCT((RAW_DATA!B$2:B$5000=B11)*(RAW_DATA!C$2:C$5000=A11)*(RAW_DATA!E$2:E$5000="Housing")*RAW_DATA!H$2:H$5000) -> 8724 | I11: =SUMPRODUCT((RAW_DATA!B$2:B$5000=B11)*(RAW_DATA!C$2:C$5000=A11)*(RAW_DATA!E$2:E$5000="Food")*RAW_DATA!H$2:H$5000) -> 2340 | J11: =SUMPRODUCT((RAW_DATA!B$2:B$5000=B11)*(RAW_DATA!C$2:C$5000=A11)*(RAW_DATA!E$2:E$5000="Transport")*RAW_DATA!H$2:H$5000) -> 0 | K11: =SUMPRODUCT((RAW_DATA!B$2:B$5000=B11)*(RAW_DATA!C$2:C$5000=A11)*(RAW_DATA!E$2:E$5000="Health")*RAW_DATA!H$2:H$5000) -> 1304 | L11: =SUMPRODUCT((RAW_DATA!B$2:B$5000=B11)*(RAW_DATA!C$2:C$5000=A11)*(RAW_DATA!E$2:E$5000="Shopping")*RAW_DATA!H$2:H$5000) -> 2134 | M11: =SUMPRODUCT((RAW_DATA!B$2:B$5000=B11)*(RAW_DATA!C$2:C$5000=A11)*(RAW_DATA!E$2:E$5000="Entertainment")*RAW_DATA!H$2:H$5000) -> 0 | N11: =SUMPRODUCT((RAW_DATA!B$2:B$5000=B11)*(RAW_DATA!C$2:C$5000=A11)*(RAW_DATA!E$2:E$5000="Education")*RAW_DATA!H$2:H$5000) -> 0 | O11: =SUMPRODUCT((RAW_DATA!B$2:B$5000=B11)*(RAW_DATA!C$2:C$5000=A11)*(RAW_DATA!E$2:E$5000="Others")*RAW_DATA!H$2:H$5000) -> 801 | P11: =P10+E11+F11 -> 493679
A12: 2023 | B12: Oct | C12: =SUMPRODUCT((RAW_DATA!B$2:B$5000=B12)*(RAW_DATA!C$2:C$5000=A12)*(RAW_DATA!D$2:D$5000="Income")*RAW_DATA!H$2:H$5000) -> 78238 | D12: =SUMPRODUCT((RAW_DATA!B$2:B$5000=B12)*(RAW_DATA!C$2:C$5000=A12)*(RAW_DATA!D$2:D$5000="Expense")*RAW_DATA!H$2:H$5000) -> 12828 | E12: =SUMPRODUCT((RAW_DATA!B$2:B$5000=B12)*(RAW_DATA!C$2:C$5000=A12)*(RAW_DATA!D$2:D$5000="Savings")*RAW_DATA!H$2:H$5000) -> 10000 | F12: =C12-D12-E12 -> 55410 | G12: =IF(C12>0,(E12+F12)/C12,0) -> 0.83603875 | H12: =SUMPRODUCT((RAW_DATA!B$2:B$5000=B12)*(RAW_DATA!C$2:C$5000=A12)*(RAW_DATA!E$2:E$5000="Housing")*RAW_DATA!H$2:H$5000) -> 8579 | I12: =SUMPRODUCT((RAW_DATA!B$2:B$5000=B12)*(RAW_DATA!C$2:C$5000=A12)*(RAW_DATA!E$2:E$5000="Food")*RAW_DATA!H$2:H$5000) -> 0 | J12: =SUMPRODUCT((RAW_DATA!B$2:B$5000=B12)*(RAW_DATA!C$2:C$5000=A12)*(RAW_DATA!E$2:E$5000="Transport")*RAW_DATA!H$2:H$5000) -> 0 | K12: =SUMPRODUCT((RAW_DATA!B$2:B$5000=B12)*(RAW_DATA!C$2:C$5000=A12)*(RAW_DATA!E$2:E$5000="Health")*RAW_DATA!H$2:H$5000) -> 1546 | L12: =SUMPRODUCT((RAW_DATA!B$2:B$5000=B12)*(RAW_DATA!C$2:C$5000=A12)*(RAW_DATA!E$2:E$5000="Shopping")*RAW_DATA!H$2:H$5000) -> 0 | M12: =SUMPRODUCT((RAW_DATA!B$2:B$5000=B12)*(RAW_DATA!C$2:C$5000=A12)*(RAW_DATA!E$2:E$5000="Entertainment")*RAW_DATA!H$2:H$5000) -> 969 | N12: =SUMPRODUCT((RAW_DATA!B$2:B$5000=B12)*(RAW_DATA!C$2:C$5000=A12)*(RAW_DATA!E$2:E$5000="Education")*RAW_DATA!H$2:H$5000) -> 1734 | O12: =SUMPRODUCT((RAW_DATA!B$2:B$5000=B12)*(RAW_DATA!C$2:C$5000=A12)*(RAW_DATA!E$2:E$5000="Others")*RAW_DATA!H$2:H$5000) -> 0 | P12: =P11+E12+F12 -> 559089
A13: 2023 | B13: Nov | C13: =SUMPRODUCT((RAW_DATA!B$2:B$5000=B13)*(RAW_DATA!C$2:C$5000=A13)*(RAW_DATA!D$2:D$5000="Income")*RAW_DATA!H$2:H$5000) -> 65000 | D13: =SUMPRODUCT((RAW_DATA!B$2:B$5000=B13)*(RAW_DATA!C$2:C$5000=A13)*(RAW_DATA!D$2:D$5000="Expense")*RAW_DATA!H$2:H$5000) -> 21242 | E13: =SUMPRODUCT((RAW_DATA!B$2:B$5000=B13)*(RAW_DATA!C$2:C$5000=A13)*(RAW_DATA!D$2:D$5000="Savings")*RAW_DATA!H$2:H$5000) -> 10000 | F13: =C13-D13-E13 -> 33758 | G13: =IF(C13>0,(E13+F13)/C13,0) -> 0.6732 | H13: =SUMPRODUCT((RAW_DATA!B$2:B$5000=B13)*(RAW_DATA!C$2:C$5000=A13)*(RAW_DATA!E$2:E$5000="Housing")*RAW_DATA!H$2:H$5000) -> 13491 | I13: =SUMPRODUCT((RAW_DATA!B$2:B$5000=B13)*(RAW_DATA!C$2:C$5000=A13)*(RAW_DATA!E$2:E$5000="Food")*RAW_DATA!H$2:H$5000) -> 0 | J13: =SUMPRODUCT((RAW_DATA!B$2:B$5000=B13)*(RAW_DATA!C$2:C$5000=A13)*(RAW_DATA!E$2:E$5000="Transport")*RAW_DATA!H$2:H$5000) -> 1050 | K13: =SUMPRODUCT((RAW_DATA!B$2:B$5000=B13)*(RAW_DATA!C$2:C$5000=A13)*(RAW_DATA!E$2:E$5000="Health")*RAW_DATA!H$2:H$5000) -> 1434 | L13: =SUMPRODUCT((RAW_DATA!B$2:B$5000=B13)*(RAW_DATA!C$2:C$5000=A13)*(RAW_DATA!E$2:E$5000="Shopping")*RAW_DATA!H$2:H$5000) -> 3294 | M13: =SUMPRODUCT((RAW_DATA!B$2:B$5000=B13)*(RAW_DATA!C$2:C$5000=A13)*(RAW_DATA!E$2:E$5000="Entertainment")*RAW_DATA!H$2:H$5000) -> 1223 | N13: =SUMPRODUCT((RAW_DATA!B$2:B$5000=B13)*(RAW_DATA!C$2:C$5000=A13)*(RAW_DATA!E$2:E$5000="Education")*RAW_DATA!H$2:H$5000) -> 0 | O13: =SUMPRODUCT((RAW_DATA!B$2:B$5000=B13)*(RAW_DATA!C$2:C$5000=A13)*(RAW_DATA!E$2:E$5000="Others")*RAW_DATA!H$2:H$5000) -> 750 | P13: =P12+E13+F13 -> 602847
A14: 2023 | B14: Dec | C14: =SUMPRODUCT((RAW_DATA!B$2:B$5000=B14)*(RAW_DATA!C$2:C$5000=A14)*(RAW_DATA!D$2:D$5000="Income")*RAW_DATA!H$2:H$5000) -> 72546 | D14: =SUMPRODUCT((RAW_DATA!B$2:B$5000=B14)*(RAW_DATA!C$2:C$5000=A14)*(RAW_DATA!D$2:D$5000="Expense")*RAW_DATA!H$2:H$5000) -> 8977 | E14: =SUMPRODUCT((RAW_DATA!B$2:B$5000=B14)*(RAW_DATA!C$2:C$5000=A14)*(RAW_DATA!D$2:D$5000="Savings")*RAW_DATA!H$2:H$5000) -> 15000 | F14: =C14-D14-E14 -> 48569 | G14: =IF(C14>0,(E14+F14)/C14,0) -> 0.87625782 | H14: =SUMPRODUCT((RAW_DATA!B$2:B$5000=B14)*(RAW_DATA!C$2:C$5000=A14)*(RAW_DATA!E$2:E$5000="Housing")*RAW_DATA!H$2:H$5000) -> 0 | I14: =SUMPRODUCT((RAW_DATA!B$2:B$5000=B14)*(RAW_DATA!C$2:C$5000=A14)*(RAW_DATA!E$2:E$5000="Food")*RAW_DATA!H$2:H$5000) -> 2933 | J14: =SUMPRODUCT((RAW_DATA!B$2:B$5000=B14)*(RAW_DATA!C$2:C$5000=A14)*(RAW_DATA!E$2:E$5000="Transport")*RAW_DATA!H$2:H$5000) -> 1004 | K14: =SUMPRODUCT((RAW_DATA!B$2:B$5000=B14)*(RAW_DATA!C$2:C$5000=A14)*(RAW_DATA!E$2:E$5000="Health")*RAW_DATA!H$2:H$5000) -> 727 | L14: =SUMPRODUCT((RAW_DATA!B$2:B$5000=B14)*(RAW_DATA!C$2:C$5000=A14)*(RAW_DATA!E$2:E$5000="Shopping")*RAW_DATA!H$2:H$5000) -> 2161 | M14: =SUMPRODUCT((RAW_DATA!B$2:B$5000=B14)*(RAW_DATA!C$2:C$5000=A14)*(RAW_DATA!E$2:E$5000="Entertainment")*RAW_DATA!H$2:H$5000) -> 1114 | N14: =SUMPRODUCT((RAW_DATA!B$2:B$5000=B14)*(RAW_DATA!C$2:C$5000=A14)*(RAW_DATA!E$2:E$5000="Education")*RAW_DATA!H$2:H$5000) -> 0 | O14: =SUMPRODUCT((RAW_DATA!B$2:B$5000=B14)*(RAW_DATA!C$2:C$5000=A14)*(RAW_DATA!E$2:E$5000="Others")*RAW_DATA!H$2:H$5000) -> 1038 | P14: =P13+E14+F14 -> 666416
A15: 2024 | B15: Jan | C15: =SUMPRODUCT((RAW_DATA!B$2:B$5000=B15)*(RAW_DATA!C$2:C$5000=A15)*(RAW_DATA!D$2:D$5000="Income")*RAW_DATA!H$2:H$5000) -> 72426 | D15: =SUMPRODUCT((RAW_DATA!B$2:B$5000=B15)*(RAW_DATA!C$2:C$5000=A15)*(RAW_DATA!D$2:D$5000="Expense")*RAW_DATA!H$2:H$5000) -> 23496 | E15: =SUMPRODUCT((RAW_DATA!B$2:B$5000=B15)*(RAW_DATA!C$2:C$5000=A15)*(RAW_DATA!D$2:D$5000="Savings")*RAW_DATA!H$2:H$5000) -> 10000 | F15: =C15-D15-E15 -> 38930 | G15: =IF(C15>0,(E15+F15)/C15,0) -> 0.67558612 | H15: =SUMPRODUCT((RAW_DATA!B$2:B$5000=B15)*(RAW_DATA!C$2:C$5000=A15)*(RAW_DATA!E$2:E$5000="Housing")*RAW_DATA!H$2:H$5000) -> 11050 | I15: =SUMPRODUCT((RAW_DATA!B$2:B$5000=B15)*(RAW_DATA!C$2:C$5000=A15)*(RAW_DATA!E$2:E$5000="Food")*RAW_DATA!H$2:H$5000) -> 4893 | J15: =SUMPRODUCT((RAW_DATA!B$2:B$5000=B15)*(RAW_DATA!C$2:C$5000=A15)*(RAW_DATA!E$2:E$5000="Transport")*RAW_DATA!H$2:H$5000) -> 2171 | K15: =SUMPRODUCT((RAW_DATA!B$2:B$5000=B15)*(RAW_DATA!C$2:C$5000=A15)*(RAW_DATA!E$2:E$5000="Health")*RAW_DATA!H$2:H$5000) -> 1052 | L15: =SUMPRODUCT((RAW_DATA!B$2:B$5000=B15)*(RAW_DATA!C$2:C$5000=A15)*(RAW_DATA!E$2:E$5000="Shopping")*RAW_DATA!H$2:H$5000) -> 2234 | M15: =SUMPRODUCT((RAW_DATA!B$2:B$5000=B15)*(RAW_DATA!C$2:C$5000=A15)*(RAW_DATA!E$2:E$5000="Entertainment")*RAW_DATA!H$2:H$5000) -> 1225 | N15: =SUMPRODUCT((RAW_DATA!B$2:B$5000=B15)*(RAW_DATA!C$2:C$5000=A15)*(RAW_DATA!E$2:E$5000="Education")*RAW_DATA!H$2:H$5000) -> 0 | O15: =SUMPRODUCT((RAW_DATA!B$2:B$5000=B15)*(RAW_DATA!C$2:C$5000=A15)*(RAW_DATA!E$2:E$5000="Others")*RAW_DATA!H$2:H$5000) -> 871 | P15: =P14+E15+F15 -> 715346
... A26: 2024 | B26: Dec | C26: =SUMPRODUCT((RAW_DATA!B$2:B$5000=B26)*(RAW_DATA!C$2:C$5000=A26)*(RAW_DATA!D$2:D$5000="Income")*RAW_DATA!H$2:H$5000) -> 65000 | D26: =SUMPRODUCT((RAW_DATA!B$2:B$5000=B26)*(RAW_DATA!C$2:C$5000=A26)*(RAW_DATA!D$2:D$5000="Expense")*RAW_DATA!H$2:H$5000) -> 18370 | E26: =SUMPRODUCT((RAW_DATA!B$2:B$5000=B26)*(RAW_DATA!C$2:C$5000=A26)*(RAW_DATA!D$2:D$5000="Savings")*RAW_DATA!H$2:H$5000) -> 15000 | F26: =C26-D26-E26 -> 31630 | G26: =IF(C26>0,(E26+F26)/C26,0) -> 0.71738462 | H26: =SUMPRODUCT((RAW_DATA!B$2:B$5000=B26)*(RAW_DATA!C$2:C$5000=A26)*(RAW_DATA!E$2:E$5000="Housing")*RAW_DATA!H$2:H$5000) -> 14041 | I26: =SUMPRODUCT((RAW_DATA!B$2:B$5000=B26)*(RAW_DATA!C$2:C$5000=A26)*(RAW_DATA!E$2:E$5000="Food")*RAW_DATA!H$2:H$5000) -> 0 | J26: =SUMPRODUCT((RAW_DATA!B$2:B$5000=B26)*(RAW_DATA!C$2:C$5000=A26)*(RAW_DATA!E$2:E$5000="Transport")*RAW_DATA!H$2:H$5000) -> 0 | K26: =SUMPRODUCT((RAW_DATA!B$2:B$5000=B26)*(RAW_DATA!C$2:C$5000=A26)*(RAW_DATA!E$2:E$5000="Health")*RAW_DATA!H$2:H$5000) -> 1475 | L26: =SUMPRODUCT((RAW_DATA!B$2:B$5000=B26)*(RAW_DATA!C$2:C$5000=A26)*(RAW_DATA!E$2:E$5000="Shopping")*RAW_DATA!H$2:H$5000) -> 2854 | M26: =SUMPRODUCT((RAW_DATA!B$2:B$5000=B26)*(RAW_DATA!C$2:C$5000=A26)*(RAW_DATA!E$2:E$5000="Entertainment")*RAW_DATA!H$2:H$5000) -> 0 | N26: =SUMPRODUCT((RAW_DATA!B$2:B$5000=B26)*(RAW_DATA!C$2:C$5000=A26)*(RAW_DATA!E$2:E$5000="Education")*RAW_DATA!H$2:H$5000) -> 0 | O26: =SUMPRODUCT((RAW_DATA!B$2:B$5000=B26)*(RAW_DATA!C$2:C$5000=A26)*(RAW_DATA!E$2:E$5000="Others")*RAW_DATA!H$2:H$5000) -> 0 | P26: =P25+E26+F26 -> 1292784

Sheet ANNUAL_SUMMARY
A1: 📅 ANNUAL PERFORMANCE SUMMARY
A2: Year | B2: Total Income | C2: Total Expense | D2: Total Savings | E2: Net Cash Flow | F2: Savings Rate % | G2: YoY Income Growth | H2: YoY Expense Growth
A3: 2023 | B3: =SUMPRODUCT((MONTHLY_SUMMARY!A$3:A$30=A3)*MONTHLY_SUMMARY!C$3:C$30) -> 870056 | C3: =SUMPRODUCT((MONTHLY_SUMMARY!A$3:A$30=A3)*MONTHLY_SUMMARY!D$3:D$30) -> 203640 | D3: =SUMPRODUCT((MONTHLY_SUMMARY!A$3:A$30=A3)*MONTHLY_SUMMARY!E$3:E$30) -> 140000 | E3: =B3-C3-D3 -> 526416 | F3: =IF(B3>0,(D3+E3)/B3,0) -> 0.7659461 | G3: "-" | H3: "-"
A4: 2024 | B4: =SUMPRODUCT((MONTHLY_SUMMARY!A$3:A$30=A4)*MONTHLY_SUMMARY!C$3:C$30) -> 833837 | C4: =SUMPRODUCT((MONTHLY_SUMMARY!A$3:A$30=A4)*MONTHLY_SUMMARY!D$3:D$30) -> 207469 | D4: =SUMPRODUCT((MONTHLY_SUMMARY!A$3:A$30=A4)*MONTHLY_SUMMARY!E$3:E$30) -> 140000 | E4: =B4-C4-D4 -> 486368 | F4: =IF(B4>0,(D4+E4)/B4,0) -> 0.75118758 | G4: =IF(B3>0,(B4-B3)/B3,0) -> -0.041628355 | H4: =IF(C3>0,(C4-C3)/C3,0) -> 0.018802789

Sheet CATEGORY_ANALYSIS
A1: 🏷️ CATEGORY-WISE SPENDING ANALYSIS
A3: Select Year: | B3: 2024
A5: Category | B5: 2023 Total | C5: 2024 Total | D5: Change ₹ | E5: Change % | F5: % of Total Spend
A6: Housing | B6: =SUMPRODUCT((RAW_DATA!C$2:C$5000=2023)*(RAW_DATA!D$2:D$5000="Expense")*(RAW_DATA!E$2:E$5000=A6)*RAW_DATA!H$2:H$5000) -> 98371 | C6: =SUMPRODUCT((RAW_DATA!C$2:C$5000=2024)*(RAW_DATA!D$2:D$5000="Expense")*(RAW_DATA!E$2:E$5000=A6)*RAW_DATA!H$2:H$5000) -> 92061 | D6: =C6-B6 -> -6310 | E6: =IF(B6>0,(C6-B6)/B6,0) -> -0.064144921 | F6: =IF(SUM(C$6:C$13)>0,C6/SUM(C$6:C$13),0) -> 0.44373376
A7: Food | B7: =SUMPRODUCT((RAW_DATA!C$2:C$5000=2023)*(RAW_DATA!D$2:D$5000="Expense")*(RAW_DATA!E$2:E$5000=A7)*RAW_DATA!H$2:H$5000) -> 34619 | C7: =SUMPRODUCT((RAW_DATA!C$2:C$5000=2024)*(RAW_DATA!D$2:D$5000="Expense")*(RAW_DATA!E$2:E$5000=A7)*RAW_DATA!H$2:H$5000) -> 34244 | D7: =C7-B7 -> -375 | E7: =IF(B7>0,(C7-B7)/B7,0) -> -0.010832202 | F7: =IF(SUM(C$6:C$13)>0,C7/SUM(C$6:C$13),0) -> 0.16505598
A8: Transport | B8: =SUMPRODUCT((RAW_DATA!C$2:C$5000=2023)*(RAW_DATA!D$2:D$5000="Expense")*(RAW_DATA!E$2:E$5000=A8)*RAW_DATA!H$2:H$5000) -> 10280 | C8: =SUMPRODUCT((RAW_DATA!C$2:C$5000=2024)*(RAW_DATA!D$2:D$5000="Expense")*(RAW_DATA!E$2:E$5000=A8)*RAW_DATA!H$2:H$5000) -> 14222 | D8: =C8-B8 -> 3942 | E8: =IF(B8>0,(C8-B8)/B8,0) -> 0.38346304 | F8: =IF(SUM(C$6:C$13)>0,C8/SUM(C$6:C$13),0) -> 0.06855
A9: Health | B9: =SUMPRODUCT((RAW_DATA!C$2:C$5000=2023)*(RAW_DATA!D$2:D$5000="Expense")*(RAW_DATA!E$2:E$5000=A9)*RAW_DATA!H$2:H$5000) -> 5011 | C9: =SUMPRODUCT((RAW_DATA!C$2:C$5000=2024)*(RAW_DATA!D$2:D$5000="Expense")*(RAW_DATA!E$2:E$5000=A9)*RAW_DATA!H$2:H$5000) -> 14002 | D9: =C9-B9 -> 8991 | E9: =IF(B9>0,(C9-B9)/B9,0) -> 1.7942526 | F9: =IF(SUM(C$6:C$13)>0,C9/SUM(C$6:C$13),0) -> 0.067489601
A10: Shopping | B10: =SUMPRODUCT((RAW_DATA!C$2:C$5000=2023)*(RAW_DATA!D$2:D$5000="Expense")*(RAW_DATA!E$2:E$5000=A10)*RAW_DATA!H$2:H$5000) -> 25042 | C10: =SUMPRODUCT((RAW_DATA!C$2:C$5000=2024)*(RAW_DATA!D$2:D$5000="Expense")*(RAW_DATA!E$2:E$5000=A10)*RAW_DATA!H$2:H$5000) -> 22551 | D10: =C10-B10 -> -2491 | E10: =IF(B10>0,(C10-B10)/B10,0) -> -0.099472886 | F10: =IF(SUM(C$6:C$13)>0,C10/SUM(C$6:C$13),0) -> 0.10869576
A11: Entertainment | B11: =SUMPRODUCT((RAW_DATA!C$2:C$5000=2023)*(RAW_DATA!D$2:D$5000="Expense")*(RAW_DATA!E$2:E$5000=A11)*RAW_DATA!H$2:H$5000) -> 8979 | C11: =SUMPRODUCT((RAW_DATA!C$2:C$5000=2024)*(RAW_DATA!D$2:D$5000="Expense")*(RAW_DATA!E$2:E$5000=A11)*RAW_DATA!H$2:H$5000) -> 5875 | D11: =C11-B11 -> -3104 | E11: =IF(B11>0,(C11-B11)/B11,0) -> -0.34569551 | F11: =IF(SUM(C$6:C$13)>0,C11/SUM(C$6:C$13),0) -> 0.028317484
A12: Education | B12: =SUMPRODUCT((RAW_DATA!C$2:C$5000=2023)*(RAW_DATA!D$2:D$5000="Expense")*(RAW_DATA!E$2:E$5000=A12)*RAW_DATA!H$2:H$5000) -> 14959 | C12: =SUMPRODUCT((RAW_DATA!C$2:C$5000=2024)*(RAW_DATA!D$2:D$5000="Expense")*(RAW_DATA!E$2:E$5000=A12)*RAW_DATA!H$2:H$5000) -> 17834 | D12: =C12-B12 -> 2875 | E12: =IF(B12>0,(C12-B12)/B12,0) -> 0.19219199 | F12: =IF(SUM(C$6:C$13)>0,C12/SUM(C$6:C$13),0) -> 0.08595983
A13: Others | B13: =SUMPRODUCT((RAW_DATA!C$2:C$5000=2023)*(RAW_DATA!D$2:D$5000="Expense")*(RAW_DATA!E$2:E$5000=A13)*RAW_DATA!H$2:H$5000) -> 6379 | C13: =SUMPRODUCT((RAW_DATA!C$2:C$5000=2024)*(RAW_DATA!D$2:D$5000="Expense")*(RAW_DATA!E$2:E$5000=A13)*RAW_DATA!H$2:H$5000) -> 6680 | D13: =C13-B13 -> 301 | E13: =IF(B13>0,(C13-B13)/B13,0) -> 0.047186079 | F13: =IF(SUM(C$6:C$13)>0,C13/SUM(C$6:C$13),0) -> 0.032197581
A14: TOTAL | B14: =SUM(B6:B13) -> 203640 | C14: =SUM(C6:C13) -> 207469 | D14: =C14-B14 -> 3829 | E14: =IF(B14>0,(C14-B14)/B14,0) -> 0.018802789 | F14: =1 -> 1

Sheet SAVINGS_TRACKER
A1: 💰 SAVINGS & INVESTMENT TRACKER
A3: SAVINGS GOALS
A4: Goal | B4: Target (₹) | C4: Saved So Far | D4: Remaining | E4: Progress % | F4: Status | G4: Target Date
A5: Emergency Fund | B5: 300000 | C5: =SUMPRODUCT((RAW_DATA!F$2:F$5000="Emergency")*RAW_DATA!H$2:H$5000) -> 0 | D5: =MAX(0,B5-C5) -> 300000 | E5: =MIN(1,IF(B5>0,C5/B5,0)) -> 0 | F5: =IF(E5>=1,"✅ Complete",IF(E5>=0.5,"🟡 On Track","🔴 Behind")) -> 🔴 Behind | G5: 2024-12
A6: International Trip | B6: 150000 | C6: =SUMPRODUCT((RAW_DATA!F$2:F$5000="Goals")*RAW_DATA!H$2:H$5000) -> 0 | D6: =MAX(0,B6-C6) -> 150000 | E6: =MIN(1,IF(B6>0,C6/B6,0)) -> 0 | F6: =IF(E6>=1,"✅ Complete",IF(E6>=0.5,"🟡 On Track","🔴 Behind")) -> 🔴 Behind | G6: 2024-06
A7: Laptop / Gadget | B7: 80000 | C7: =SUMPRODUCT((RAW_DATA!F$2:F$5000="Goals")*RAW_DATA!H$2:H$5000) -> 0 | D7: =MAX(0,B7-C7) -> 80000 | E7: =MIN(1,IF(B7>0,C7/B7,0)) -> 0 | F7: =IF(E7>=1,"✅ Complete",IF(E7>=0.5,"🟡 On Track","🔴 Behind")) -> 🔴 Behind | G7: 2024-03
A8: Higher Education | B8: 500000 | C8: =SUMPRODUCT((RAW_DATA!F$2:F$5000="Goals")*RAW_DATA!H$2:H$5000) -> 0 | D8: =MAX(0,B8-C8) -> 500000 | E8: =MIN(1,IF(B8>0,C8/B8,0)) -> 0 | F8: =IF(E8>=1,"✅ Complete",IF(E8>=0.5,"🟡 On Track","🔴 Behind")) -> 🔴 Behind | G8: 2025-12
A11: MONTHLY SAVINGS BREAKDOWN BY TYPE
A12: Month | B12: Year | C12: Mutual Fund SIP | D12: Emergency Fund | E12: Goal Savings | F12: Total Savings | G12: Savings Rate
A13: Jan | B13: 2023 | C13: =SUMPRODUCT((RAW_DATA!B$2:B$5000=A13)*(RAW_DATA!C$2:C$5000=B13)*(RAW_DATA!F$2:F$5000="Mutual Fund SIP")*RAW_DATA!H$2:H$5000) -> 10000 | D13: =SUMPRODUCT((RAW_DATA!B$2:B$5000=A13)*(RAW_DATA!C$2:C$5000=B13)*(RAW_DATA!F$2:F$5000="Emergency Fund")*RAW_DATA!H$2:H$5000) -> 0 | E13: =SUMPRODUCT((RAW_DATA!B$2:B$5000=A13)*(RAW_DATA!C$2:C$5000=B13)*(RAW_DATA!D$2:D$5000="Savings")*RAW_DATA!H$2:H$5000)-C13-D13 -> 0 | F13: =C13+D13+E13 -> 10000 | G13: =IFERROR(F13/SUMPRODUCT((RAW_DATA!B$2:B$5000=A13)*(RAW_DATA!C$2:C$5000=B13)*(RAW_DATA!D$2:D$5000="Income")*RAW_DATA!H$2:H$5000),0) -> 0.1420273
A14: Feb | B14: 2023 | C14: =SUMPRODUCT((RAW_DATA!B$2:B$5000=A14)*(RAW_DATA!C$2:C$5000=B14)*(RAW_DATA!F$2:F$5000="Mutual Fund SIP")*RAW_DATA!H$2:H$5000) -> 10000 | D14: =SUMPRODUCT((RAW_DATA!B$2:B$5000=A14)*(RAW_DATA!C$2:C$5000=B14)*(RAW_DATA!F$2:F$5000="Emergency Fund")*RAW_DATA!H$2:H$5000) -> 0 | E14: =SUMPRODUCT((RAW_DATA!B$2:B$5000=A14)*(RAW_DATA!C$2:C$5000=B14)*(RAW_DATA!D$2:D$5000="Savings")*RAW_DATA!H$2:H$5000)-C14-D14 -> 0 | F14: =C14+D14+E14 -> 10000 | G14: =IFERROR(F14/SUMPRODUCT((RAW_DATA!B$2:B$5000=A14)*(RAW_DATA!C$2:C$5000=B14)*(RAW_DATA!D$2:D$5000="Income")*RAW_DATA!H$2:H$5000),0) -> 0.15384615
A15: Mar | B15: 2023 | C15: =SUMPRODUCT((RAW_DATA!B$2:B$5000=A15)*(RAW_DATA!C$2:C$5000=B15)*(RAW_DATA!F$2:F$5000="Mutual Fund SIP")*RAW_DATA!H$2:H$5000) -> 10000 | D15: =SUMPRODUCT((RAW_DATA!B$2:B$5000=A15)*(RAW_DATA!C$2:C$5000=B15)*(RAW_DATA!F$2:F$5000="Emergency Fund")*RAW_DATA!H$2:H$5000) -> 5000 | E15: =SUMPRODUCT((RAW_DATA!B$2:B$5000=A15)*(RAW_DATA!C$2:C$5000=B15)*(RAW_DATA!D$2:D$5000="Savings")*RAW_DATA!H$2:H$5000)-C15-D15 -> 0 | F15: =C15+D15+E15 -> 15000 | G15: =IFERROR(F15/SUMPRODUCT((RAW_DATA!B$2:B$5000=A15)*(RAW_DATA!C$2:C$5000=B15)*(RAW_DATA!D$2:D$5000="Income")*RAW_DATA!H$2:H$5000),0) -> 0.18080785
A16: Apr | B16: 2023 | C16: =SUMPRODUCT((RAW_DATA!B$2:B$5000=A16)*(RAW_DATA!C$2:C$5000=B16)*(RAW_DATA!F$2:F$5000="Mutual Fund SIP")*RAW_DATA!H$2:H$5000) -> 10000 | D16: =SUMPRODUCT((RAW_DATA!B$2:B$5000=A16)*(RAW_DATA!C$2:C$5000=B16)*(RAW_DATA!F$2:F$5000="Emergency Fund")*RAW_DATA!H$2:H$5000) -> 0 | E16: =SUMPRODUCT((RAW_DATA!B$2:B$5000=A16)*(RAW_DATA!C$2:C$5000=B16)*(RAW_DATA!D$2:D$5000="Savings")*RAW_DATA!H$2:H$5000)-C16-D16 -> 0 | F16: =C16+D16+E16 -> 10000 | G16: =IFERROR(F16/SUMPRODUCT((RAW_DATA!B$2:B$5000=A16)*(RAW_DATA!C$2:C$5000=B16)*(RAW_DATA!D$2:D$5000="Income")*RAW_DATA!H$2:H$5000),0) -> 0.15384615
A17: May | B17: 2023 | C17: =SUMPRODUCT((RAW_DATA!B$2:B$5000=A17)*(RAW_DATA!C$2:C$5000=B17)*(RAW_DATA!F$2:F$5000="Mutual Fund SIP")*RAW_DATA!H$2:H$5000) -> 10000 | D17: =SUMPRODUCT((RAW_DATA!B$2:B$5000=A17)*(RAW_DATA!C$2:C$5000=B17)*(RAW_DATA!F$2:F$5000="Emergency Fund")*RAW_DATA!H$2:H$5000) -> 0 | E17: =SUMPRODUCT((RAW_DATA!B$2:B$5000=A17)*(RAW_DATA!C$2:C$5000=B17)*(RAW_DATA!D$2:D$5000="Savings")*RAW_DATA!H$2:H$5000)-C17-D17 -> 0 | F17: =C17+D17+E17 -> 10000 | G17: =IFERROR(F17/SUMPRODUCT((RAW_DATA!B$2:B$5000=A17)*(RAW_DATA!C$2:C$5000=B17)*(RAW_DATA!D$2:D$5000="Income")*RAW_DATA!H$2:H$5000),0) -> 0.15384615
A18: Jun | B18: 2023 | C18: =SUMPRODUCT((RAW_DATA!B$2:B$5000=A18)*(RAW_DATA!C$2:C$5000=B18)*(RAW_DATA!F$2:F$5000="Mutual Fund SIP")*RAW_DATA!H$2:H$5000) -> 10000 | D18: =SUMPRODUCT((RAW_DATA!B$2:B$5000=A18)*(RAW_DATA!C$2:C$5000=B18)*(RAW_DATA!F$2:F$5000="Emergency Fund")*RAW_DATA!H$2:H$5000) -> 5000 | E18: =SUMPRODUCT((RAW_DATA!B$2:B$5000=A18)*(RAW_DATA!C$2:C$5000=B18)*(RAW_DATA!D$2:D$5000="Savings")*RAW_DATA!H$2:H$5000)-C18-D18 -> 0 | F18: =C18+D18+E18 -> 15000 | G18: =IFERROR(F18/SUMPRODUCT((RAW_DATA!B$2:B$5000=A18)*(RAW_DATA!C$2:C$5000=B18)*(RAW_DATA!D$2:D$5000="Income")*RAW_DATA!H$2:H$5000),0) -> 0.23076923
A19: Jul | B19: 2023 | C19: =SUMPRODUCT((RAW_DATA!B$2:B$5000=A19)*(RAW_DATA!C$2:C$5000=B19)*(RAW_DATA!F$2:F$5000="Mutual Fund SIP")*RAW_DATA!H$2:H$5000) -> 10000 | D19: =SUMPRODUCT((RAW_DATA!B$2:B$5000=A19)*(RAW_DATA!C$2:C$5000=B19)*(RAW_DATA!F$2:F$5000="Emergency Fund")*RAW_DATA!H$2:H$5000) -> 0 | E19: =SUMPRODUCT((RAW_DATA!B$2:B$5000=A19)*(RAW_DATA!C$2:C$5000=B19)*(RAW_DATA!D$2:D$5000="Savings")*RAW_DATA!H$2:H$5000)-C19-D19 -> 0 | F19: =C19+D19+E19 -> 10000 | G19: =IFERROR(F19/SUMPRODUCT((RAW_DATA!B$2:B$5000=A19)*(RAW_DATA!C$2:C$5000=B19)*(RAW_DATA!D$2:D$5000="Income")*RAW_DATA!H$2:H$5000),0) -> 0.13065576
A20: Aug | B20: 2023 | C20: =SUMPRODUCT((RAW_DATA!B$2:B$5000=A20)*(RAW_DATA!C$2:C$5000=B20)*(RAW_DATA!F$2:F$5000="Mutual Fund SIP")*RAW_DATA!H$2:H$5000) -> 10000 | D20: =SUMPRODUCT((RAW_DATA!B$2:B$5000=A20)*(RAW_DATA!C$2:C$5000=B20)*(RAW_DATA!F$2:F$5000="Emergency Fund")*RAW_DATA!H$2:H$5000) -> 0 | E20: =SUMPRODUCT((RAW_DATA!B$2:B$5000=A20)*(RAW_DATA!C$2:C$5000=B20)*(RAW_DATA!D$2:D$5000="Savings")*RAW_DATA!H$2:H$5000)-C20-D20 -> 0 | F20: =C20+D20+E20 -> 10000 | G20: =IFERROR(F20/SUMPRODUCT((RAW_DATA!B$2:B$5000=A20)*(RAW_DATA!C$2:C$5000=B20)*(RAW_DATA!D$2:D$5000="Income")*RAW_DATA!H$2:H$5000),0) -> 0.13516984
A21: Sep | B21: 2023 | C21: =SUMPRODUCT((RAW_DATA!B$2:B$5000=A21)*(RAW_DATA!C$2:C$5000=B21)*(RAW_DATA!F$2:F$5000="Mutual Fund SIP")*RAW_DATA!H$2:H$5000) -> 10000 | D21: =SUMPRODUCT((RAW_DATA!B$2:B$5000=A21)*(RAW_DATA!C$2:C$5000=B21)*(RAW_DATA!F$2:F$5000="Emergency Fund")*RAW_DATA!H$2:H$5000) -> 5000 | E21: =SUMPRODUCT((RAW_DATA!B$2:B$5000=A21)*(RAW_DATA!C$2:C$5000=B21)*(RAW_DATA!D$2:D$5000="Savings")*RAW_DATA!H$2:H$5000)-C21-D21 -> 0 | F21: =C21+D21+E21 -> 15000 | G21: =IFERROR(F21/SUMPRODUCT((RAW_DATA!B$2:B$5000=A21)*(RAW_DATA!C$2:C$5000=B21)*(RAW_DATA!D$2:D$5000="Income")*RAW_DATA!H$2:H$5000),0) -> 0.16595858
A22: Oct | B22: 2023 | C22: =SUMPRODUCT((RAW_DATA!B$2:B$5000=A22)*(RAW_DATA!C$2:C$5000=B22)*(RAW_DATA!F$2:F$5000="Mutual Fund SIP")*RAW_DATA!H$2:H$5000) -> 10000 | D22: =SUMPRODUCT((RAW_DATA!B$2:B$5000=A22)*(RAW_DATA!C$2:C$5000=B22)*(RAW_DATA!F$2:F$5000="Emergency Fund")*RAW_DATA!H$2:H$5000) -> 0 | E22: =SUMPRODUCT((RAW_DATA!B$2:B$5000=A22)*(RAW_DATA!C$2:C$5000=B22)*(RAW_DATA!D$2:D$5000="Savings")*RAW_DATA!H$2:H$5000)-C22-D22 -> 0 | F22: =C22+D22+E22 -> 10000 | G22: =IFERROR(F22/SUMPRODUCT((RAW_DATA!B$2:B$5000=A22)*(RAW_DATA!C$2:C$5000=B22)*(RAW_DATA!D$2:D$5000="Income")*RAW_DATA!H$2:H$5000),0) -> 0.12781513
A23: Nov | B23: 2023 | C23: =SUMPRODUCT((RAW_DATA!B$2:B$5000=A23)*(RAW_DATA!C$2:C$5000=B23)*(RAW_DATA!F$2:F$5000="Mutual Fund SIP")*RAW_DATA!H$2:H$5000) -> 10000 | D23: =SUMPRODUCT((RAW_DATA!B$2:B$5000=A23)*(RAW_DATA!C$2:C$5000=B23)*(RAW_DATA!F$2:F$5000="Emergency Fund")*RAW_DATA!H$2:H$5000) -> 0 | E23: =SUMPRODUCT((RAW_DATA!B$2:B$5000=A23)*(RAW_DATA!C$2:C$5000=B23)*(RAW_DATA!D$2:D$5000="Savings")*RAW_DATA!H$2:H$5000)-C23-D23 -> 0 | F23: =C23+D23+E23 -> 10000 | G23: =IFERROR(F23/SUMPRODUCT((RAW_DATA!B$2:B$5000=A23)*(RAW_DATA!C$2:C$5000=B23)*(RAW_DATA!D$2:D$5000="Income")*RAW_DATA!H$2:H$5000),0) -> 0.15384615
A24: Dec | B24: 2023 | C24: =SUMPRODUCT((RAW_DATA!B$2:B$5000=A24)*(RAW_DATA!C$2:C$5000=B24)*(RAW_DATA!F$2:F$5000="Mutual Fund SIP")*RAW_DATA!H$2:H$5000) -> 10000 | D24: =SUMPRODUCT((RAW_DATA!B$2:B$5000=A24)*(RAW_DATA!C$2:C$5000=B24)*(RAW_DATA!F$2:F$5000="Emergency Fund")*RAW_DATA!H$2:H$5000) -> 5000 | E24: =SUMPRODUCT((RAW_DATA!B$2:B$5000=A24)*(RAW_DATA!C$2:C$5000=B24)*(RAW_DATA!D$2:D$5000="Savings")*RAW_DATA!H$2:H$5000)-C24-D24 -> 0 | F24: =C24+D24+E24 -> 15000 | G24: =IFERROR(F24/SUMPRODUCT((RAW_DATA!B$2:B$5000=A24)*(RAW_DATA!C$2:C$5000=B24)*(RAW_DATA!D$2:D$5000="Income")*RAW_DATA!H$2:H$5000),0) -> 0.20676536
... A36: Dec | B36: 2024 | C36: =SUMPRODUCT((RAW_DATA!B$2:B$5000=A36)*(RAW_DATA!C$2:C$5000=B36)*(RAW_DATA!F$2:F$5000="Mutual Fund SIP")*RAW_DATA!H$2:H$5000) -> 10000 | D36: =SUMPRODUCT((RAW_DATA!B$2:B$5000=A36)*(RAW_DATA!C$2:C$5000=B36)*(RAW_DATA!F$2:F$5000="Emergency Fund")*RAW_DATA!H$2:H$5000) -> 5000 | E36: =SUMPRODUCT((RAW_DATA!B$2:B$5000=A36)*(RAW_DATA!C$2:C$5000=B36)*(RAW_DATA!D$2:D$5000="Savings")*RAW_DATA!H$2:H$5000)-C36-D36 -> 0 | F36: =C36+D36+E36 -> 15000 | G36: =IFERROR(F36/SUMPRODUCT((RAW_DATA!B$2:B$5000=A36)*(RAW_DATA!C$2:C$5000=B36)*(RAW_DATA!D$2:D$5000="Income")*RAW_DATA!H$2:H$5000),0) -> 0.23076923

Sheet DASHBOARD
B2: 💼 PERSONAL FINANCE DASHBOARD | FY 2024
B4: TOTAL INCOME | E4: TOTAL EXPENSES | H4: TOTAL SAVINGS | K4: SAVINGS RATE
B5: =ANNUAL_SUMMARY!B4 -> 833837 | E5: =ANNUAL_SUMMARY!C4 -> 207469 | H5: =ANNUAL_SUMMARY!D4 -> 140000 | K5: =ANNUAL_SUMMARY!F4 -> 0.75118758
B9: MONTHLY INCOME vs EXPENSE vs SAVINGS (2024)
B10: Month | C10: Income | D10: Expense | E10: Savings | F10: Savings Rate
B11: Jan | C11: =SUMPRODUCT((MONTHLY_SUMMARY!B$3:B$30=B11)*(MONTHLY_SUMMARY!A$3:A$30=2024)*MONTHLY_SUMMARY!C$3:C$30) -> 72426 | D11: =SUMPRODUCT((MONTHLY_SUMMARY!B$3:B$30=B11)*(MONTHLY_SUMMARY!A$3:A$30=2024)*MONTHLY_SUMMARY!D$3:D$30) -> 23496 | E11: =SUMPRODUCT((MONTHLY_SUMMARY!B$3:B$30=B11)*(MONTHLY_SUMMARY!A$3:A$30=2024)*MONTHLY_SUMMARY!E$3:E$30) -> 10000 | F11: =IF(C11>0,E11/C11,0) -> 0.13807196
B12: Feb | C12: =SUMPRODUCT((MONTHLY_SUMMARY!B$3:B$30=B12)*(MONTHLY_SUMMARY!A$3:A$30=2024)*MONTHLY_SUMMARY!C$3:C$30) -> 65000 | D12: =SUMPRODUCT((MONTHLY_SUMMARY!B$3:B$30=B12)*(MONTHLY_SUMMARY!A$3:A$30=2024)*MONTHLY_SUMMARY!D$3:D$30) -> 18556 | E12: =SUMPRODUCT((MONTHLY_SUMMARY!B$3:B$30=B12)*(MONTHLY_SUMMARY!A$3:A$30=2024)*MONTHLY_SUMMARY!E$3:E$30) -> 10000 | F12: =IF(C12>0,E12/C12,0) -> 0.15384615
B13: Mar | C13: =SUMPRODUCT((MONTHLY_SUMMARY!B$3:B$30=B13)*(MONTHLY_SUMMARY!A$3:A$30=2024)*MONTHLY_SUMMARY!C$3:C$30) -> 76894 | D13: =SUMPRODUCT((MONTHLY_SUMMARY!B$3:B$30=B13)*(MONTHLY_SUMMARY!A$3:A$30=2024)*MONTHLY_SUMMARY!D$3:D$30) -> 16013 | E13: =SUMPRODUCT((MONTHLY_SUMMARY!B$3:B$30=B13)*(MONTHLY_SUMMARY!A$3:A$30=2024)*MONTHLY_SUMMARY!E$3:E$30) -> 15000 | F13: =IF(C13>0,E13/C13,0) -> 0.19507374
B14: Apr | C14: =SUMPRODUCT((MONTHLY_SUMMARY!B$3:B$30=B14)*(MONTHLY_SUMMARY!A$3:A$30=2024)*MONTHLY_SUMMARY!C$3:C$30) -> 65000 | D14: =SUMPRODUCT((MONTHLY_SUMMARY!B$3:B$30=B14)*(MONTHLY_SUMMARY!A$3:A$30=2024)*MONTHLY_SUMMARY!D$3:D$30) -> 19522 | E14: =SUMPRODUCT((MONTHLY_SUMMARY!B$3:B$30=B14)*(MONTHLY_SUMMARY!A$3:A$30=2024)*MONTHLY_SUMMARY!E$3:E$30) -> 10000 | F14: =IF(C14>0,E14/C14,0) -> 0.15384615
B15: May | C15: =SUMPRODUCT((MONTHLY_SUMMARY!B$3:B$30=B15)*(MONTHLY_SUMMARY!A$3:A$30=2024)*MONTHLY_SUMMARY!C$3:C$30) -> 65000 | D15: =SUMPRODUCT((MONTHLY_SUMMARY!B$3:B$30=B15)*(MONTHLY_SUMMARY!A$3:A$30=2024)*MONTHLY_SUMMARY!D$3:D$30) -> 28005 | E15: =SUMPRODUCT((MONTHLY_SUMMARY!B$3:B$30=B15)*(MONTHLY_SUMMARY!A$3:A$30=2024)*MONTHLY_SUMMARY!E$3:E$30) -> 10000 | F15: =IF(C15>0,E15/C15,0) -> 0.15384615
B16: Jun | C16: =SUMPRODUCT((MONTHLY_SUMMARY!B$3:B$30=B16)*(MONTHLY_SUMMARY!A$3:A$30=2024)*MONTHLY_SUMMARY!C$3:C$30) -> 65000 | D16: =SUMPRODUCT((MONTHLY_SUMMARY!B$3:B$30=B16)*(MONTHLY_SUMMARY!A$3:A$30=2024)*MONTHLY_SUMMARY!D$3:D$30) -> 21787 | E16: =SUMPRODUCT((MONTHLY_SUMMARY!B$3:B$30=B16)*(MONTHLY_SUMMARY!A$3:A$30=2024)*MONTHLY_SUMMARY!E$3:E$30) -> 15000 | F16: =IF(C16>0,E16/C16,0) -> 0.23076923
B17: Jul | C17: =SUMPRODUCT((MONTHLY_SUMMARY!B$3:B$30=B17)*(MONTHLY_SUMMARY!A$3:A$30=2024)*MONTHLY_SUMMARY!C$3:C$30) -> 65000 | D17: =SUMPRODUCT((MONTHLY_SUMMARY!B$3:B$30=B17)*(MONTHLY_SUMMARY!A$3:A$30=2024)*MONTHLY_SUMMARY!D$3:D$30) -> 6019 | E17: =SUMPRODUCT((MONTHLY_SUMMARY!B$3:B$30=B17)*(MONTHLY_SUMMARY!A$3:A$30=2024)*MONTHLY_SUMMARY!E$3:E$30) -> 10000 | F17: =IF(C17>0,E17/C17,0) -> 0.15384615
B18: Aug | C18: =SUMPRODUCT((MONTHLY_SUMMARY!B$3:B$30=B18)*(MONTHLY_SUMMARY!A$3:A$30=2024)*MONTHLY_SUMMARY!C$3:C$30) -> 65000 | D18: =SUMPRODUCT((MONTHLY_SUMMARY!B$3:B$30=B18)*(MONTHLY_SUMMARY!A$3:A$30=2024)*MONTHLY_SUMMARY!D$3:D$30) -> 8693 | E18: =SUMPRODUCT((MONTHLY_SUMMARY!B$3:B$30=B18)*(MONTHLY_SUMMARY!A$3:A$30=2024)*MONTHLY_SUMMARY!E$3:E$30) -> 10000 | F18: =IF(C18>0,E18/C18,0) -> 0.15384615
B19: Sep | C19: =SUMPRODUCT((MONTHLY_SUMMARY!B$3:B$30=B19)*(MONTHLY_SUMMARY!A$3:A$30=2024)*MONTHLY_SUMMARY!C$3:C$30) -> 84241 | D19: =SUMPRODUCT((MONTHLY_SUMMARY!B$3:B$30=B19)*(MONTHLY_SUMMARY!A$3:A$30=2024)*MONTHLY_SUMMARY!D$3:D$30) -> 9513 | E19: =SUMPRODUCT((MONTHLY_SUMMARY!B$3:B$30=B19)*(MONTHLY_SUMMARY!A$3:A$30=2024)*MONTHLY_SUMMARY!E$3:E$30) -> 15000 | F19: =IF(C19>0,E19/C19,0) -> 0.17806056
B20: Oct | C20: =SUMPRODUCT((MONTHLY_SUMMARY!B$3:B$30=B20)*(MONTHLY_SUMMARY!A$3:A$30=2024)*MONTHLY_SUMMARY!C$3:C$30) -> 80276 | D20: =SUMPRODUCT((MONTHLY_SUMMARY!B$3:B$30=B20)*(MONTHLY_SUMMARY!A$3:A$30=2024)*MONTHLY_SUMMARY!D$3:D$30) -> 11565 | E20: =SUMPRODUCT((MONTHLY_SUMMARY!B$3:B$30=B20)*(MONTHLY_SUMMARY!A$3:A$30=2024)*MONTHLY_SUMMARY!E$3:E$30) -> 10000 | F20: =IF(C20>0,E20/C20,0) -> 0.12457023
B21: Nov | C21: =SUMPRODUCT((MONTHLY_SUMMARY!B$3:B$30=B21)*(MONTHLY_SUMMARY!A$3:A$30=2024)*MONTHLY_SUMMARY!C$3:C$30) -> 65000 | D21: =SUMPRODUCT((MONTHLY_SUMMARY!B$3:B$30=B21)*(MONTHLY_SUMMARY!A$3:A$30=2024)*MONTHLY_SUMMARY!D$3:D$30) -> 25930 | E21: =SUMPRODUCT((MONTHLY_SUMMARY!B$3:B$30=B21)*(MONTHLY_SUMMARY!A$3:A$30=2024)*MONTHLY_SUMMARY!E$3:E$30) -> 10000 | F21: =IF(C21>0,E21/C21,0) -> 0.15384615
B22: Dec | C22: =SUMPRODUCT((MONTHLY_SUMMARY!B$3:B$30=B22)*(MONTHLY_SUMMARY!A$3:A$30=2024)*MONTHLY_SUMMARY!C$3:C$30) -> 65000 | D22: =SUMPRODUCT((MONTHLY_SUMMARY!B$3:B$30=B22)*(MONTHLY_SUMMARY!A$3:A$30=2024)*MONTHLY_SUMMARY!D$3:D$30) -> 18370 | E22: =SUMPRODUCT((MONTHLY_SUMMARY!B$3:B$30=B22)*(MONTHLY_SUMMARY!A$3:A$30=2024)*MONTHLY_SUMMARY!E$3:E$30) -> 15000 | F22: =IF(C22>0,E22/C22,0) -> 0.23076923
B40: CATEGORY SPENDING BREAKDOWN (2024)
B41: Category | C41: 2024 Spend | D41: % of Total | E41: vs 2023
B42: Housing | C42: =SUMPRODUCT((RAW_DATA!C$2:C$5000=2024)*(RAW_DATA!D$2:D$5000="Expense")*(RAW_DATA!E$2:E$5000=B42)*RAW_DATA!H$2:H$5000) -> 92061 | D42: =IF(SUM(C42:C49)>0,C42/SUM(C$42:C$49),0) -> 0.44373376 | E42: =IFERROR((C42-SUMPRODUCT((RAW_DATA!C$2:C$5000=2023)*(RAW_DATA!D$2:D$5000="Expense")*(RAW_DATA!E$2:E$5000=B42)*RAW_DATA!H$2:H$5000))/SUMPRODUCT((RAW_DATA!C$2:C$5000=2023)*(RAW_DATA!D$2:D$5000="Expense")*(RAW_DATA!E$2:E$5000=B42)*RAW_DATA!H$2:H$5000),0) -> -0.064144921
B43: Food | C43: =SUMPRODUCT((RAW_DATA!C$2:C$5000=2024)*(RAW_DATA!D$2:D$5000="Expense")*(RAW_DATA!E$2:E$5000=B43)*RAW_DATA!H$2:H$5000) -> 34244 | D43: =IF(SUM(C42:C49)>0,C43/SUM(C$42:C$49),0) -> 0.16505598 | E43: =IFERROR((C43-SUMPRODUCT((RAW_DATA!C$2:C$5000=2023)*(RAW_DATA!D$2:D$5000="Expense")*(RAW_DATA!E$2:E$5000=B43)*RAW_DATA!H$2:H$5000))/SUMPRODUCT((RAW_DATA!C$2:C$5000=2023)*(RAW_DATA!D$2:D$5000="Expense")*(RAW_DATA!E$2:E$5000=B43)*RAW_DATA!H$2:H$5000),0) -> -0.010832202
B44: Transport | C44: =SUMPRODUCT((RAW_DATA!C$2:C$5000=2024)*(RAW_DATA!D$2:D$5000="Expense")*(RAW_DATA!E$2:E$5000=B44)*RAW_DATA!H$2:H$5000) -> 14222 | D44: =IF(SUM(C42:C49)>0,C44/SUM(C$42:C$49),0) -> 0.06855 | E44: =IFERROR((C44-SUMPRODUCT((RAW_DATA!C$2:C$5000=2023)*(RAW_DATA!D$2:D$5000="Expense")*(RAW_DATA!E$2:E$5000=B44)*RAW_DATA!H$2:H$5000))/SUMPRODUCT((RAW_DATA!C$2:C$5000=2023)*(RAW_DATA!D$2:D$5000="Expense")*(RAW_DATA!E$2:E$5000=B44)*RAW_DATA!H$2:H$5000),0) -> 0.38346304
B45: Health | C45: =SUMPRODUCT((RAW_DATA!C$2:C$5000=2024)*(RAW_DATA!D$2:D$5000="Expense")*(RAW_DATA!E$2:E$5000=B45)*RAW_DATA!H$2:H$5000) -> 14002 | D45: =IF(SUM(C42:C49)>0,C45/SUM(C$42:C$49),0) -> 0.067489601 | E45: =IFERROR((C45-SUMPRODUCT((RAW_DATA!C$2:C$5000=2023)*(RAW_DATA!D$2:D$5000="Expense")*(RAW_DATA!E$2:E$5000=B45)*RAW_DATA!H$2:H$5000))/SUMPRODUCT((RAW_DATA!C$2:C$5000=2023)*(RAW_DATA!D$2:D$5000="Expense")*(RAW_DATA!E$2:E$5000=B45)*RAW_DATA!H$2:H$5000),0) -> 1.7942526
B46: Shopping | C46: =SUMPRODUCT((RAW_DATA!C$2:C$5000=2024)*(RAW_DATA!D$2:D$5000="Expense")*(RAW_DATA!E$2:E$5000=B46)*RAW_DATA!H$2:H$5000) -> 22551 | D46: =IF(SUM(C42:C49)>0,C46/SUM(C$42:C$49),0) -> 0.10869576 | E46: =IFERROR((C46-SUMPRODUCT((RAW_DATA!C$2:C$5000=2023)*(RAW_DATA!D$2:D$5000="Expense")*(RAW_DATA!E$2:E$5000=B46)*RAW_DATA!H$2:H$5000))/SUMPRODUCT((RAW_DATA!C$2:C$5000=2023)*(RAW_DATA!D$2:D$5000="Expense")*(RAW_DATA!E$2:E$5000=B46)*RAW_DATA!H$2:H$5000),0) -> -0.099472886
B47: Entertainment | C47: =SUMPRODUCT((RAW_DATA!C$2:C$5000=2024)*(RAW_DATA!D$2:D$5000="Expense")*(RAW_DATA!E$2:E$5000=B47)*RAW_DATA!H$2:H$5000) -> 5875 | D47: =IF(SUM(C42:C49)>0,C47/SUM(C$42:C$49),0) -> 0.028317484 | E47: =IFERROR((C47-SUMPRODUCT((RAW_DATA!C$2:C$5000=2023)*(RAW_DATA!D$2:D$5000="Expense")*(RAW_DATA!E$2:E$5000=B47)*RAW_DATA!H$2:H$5000))/SUMPRODUCT((RAW_DATA!C$2:C$5000=2023)*(RAW_DATA!D$2:D$5000="Expense")*(RAW_DATA!E$2:E$5000=B47)*RAW_DATA!H$2:H$5000),0) -> -0.34569551
B48: Education | C48: =SUMPRODUCT((RAW_DATA!C$2:C$5000=2024)*(RAW_DATA!D$2:D$5000="Expense")*(RAW_DATA!E$2:E$5000=B48)*RAW_DATA!H$2:H$5000) -> 17834 | D48: =IF(SUM(C42:C49)>0,C48/SUM(C$42:C$49),0) -> 0.08595983 | E48: =IFERROR((C48-SUMPRODUCT((RAW_DATA!C$2:C$5000=2023)*(RAW_DATA!D$2:D$5000="Expense")*(RAW_DATA!E$2:E$5000=B48)*RAW_DATA!H$2:H$5000))/SUMPRODUCT((RAW_DATA!C$2:C$5000=2023)*(RAW_DATA!D$2:D$5000="Expense")*(RAW_DATA!E$2:E$5000=B48)*RAW_DATA!H$2:H$5000),0) -> 0.19219199
B49: Others | C49: =SUMPRODUCT((RAW_DATA!C$2:C$5000=2024)*(RAW_DATA!D$2:D$5000="Expense")*(RAW_DATA!E$2:E$5000=B49)*RAW_DATA!H$2:H$5000) -> 6680 | D49: =IF(SUM(C42:C49)>0,C49/SUM(C$42:C$49),0) -> 0.032197581 | E49: =IFERROR((C49-SUMPRODUCT((RAW_DATA!C$2:C$5000=2023)*(RAW_DATA!D$2:D$5000="Expense")*(RAW_DATA!E$2:E$5000=B49)*RAW_DATA!H$2:H$5000))/SUMPRODUCT((RAW_DATA!C$2:C$5000=2023)*(RAW_DATA!D$2:D$5000="Expense")*(RAW_DATA!E$2:E$5000=B49)*RAW_DATA!H$2:H$5000),0) -> 0.047186079

Sheet INSTRUCTIONS
A1: 📖 FORMULA GUIDE & INSTRUCTIONS
A3: SHEET OVERVIEW
A4: Sheet | B4: Purpose | C4: Key Features
A5: RAW_DATA | B5: Log all transactions here | C5: Formatted table, drop-down for Type, auto-categorisation
A6: MONTHLY_SUMMARY | B6: Auto-calculated monthly P&L | C6: SUMPRODUCT formulas, conditional formatting
A7: ANNUAL_SUMMARY | B7: Year-over-year comparison | C7: YoY growth %, aggregated from monthly
A8: CATEGORY_ANALYSIS | B8: Spending by category | C8: Year selector, color-scale heatmap
A9: SAVINGS_TRACKER | B9: Goal tracking + SIP breakdown | C9: Goal progress, savings by sub-category
A10: DASHBOARD | B10: Executive KPI view | C10: KPI cards, clustered bar chart, pie chart, line chart
A12: COLOR CODING LEGEND
A13: Color | B13: Meaning
A14: Blue text | B14: Hardcoded input — change freely (e.g. targets, year selector)
A15: Black text | B15: Formula — do NOT edit
A16: Green text | B16: Cross-sheet link
A17: Yellow fill | B17: Cell that needs your input or attention
A19: KEY FORMULAS USED
A20: Formula | B20: Purpose | C20: Example
A21: SUMPRODUCT | B21: Multi-condition sum (replaces SUMIFS for array logic) | C21: SUMPRODUCT((A:A=Year)*(B:B=Month)*(D:D=Income)*H:H)
A22: XLOOKUP / IFERROR | B22: Safe lookups with fallback | C22: IFERROR(XLOOKUP(...), 0)
A23: Conditional Formatting | B23: ColorScale for savings rate, CellIsRule for negatives | C23: Applied on G col in MONTHLY_SUMMARY
A24: DataValidation | B24: Drop-down lists for Type and Year | C24: D column in RAW_DATA, B3 in CATEGORY_ANALYSIS
A25: Named Table (Transactions) | B25: Structured ref in RAW_DATA | C25: Insert → Table on RAW_DATA
A27: HOW TO ADD NEW DATA
A28: Step | B28: Action
A29: 1 | B29: Go to RAW_DATA sheet
A30: 2 | B30: Add a new row below the last transaction
A31: 3 | B31: Fill: Date, Month, Year, Type (Income/Expense/Savings), Category, Sub-Category, Description, Amount, Account
A32: 4 | B32: All summary sheets update automatically — no manual refresh needed
A33: 5 | B33: To add a new year, extend MONTHLY_SUMMARY rows with the same SUMPRODUCT pattern
A35: POWER QUERY NOTE
A36: Feature | B36: How to Enable
A37: Power Query Refresh | B37: Data → Get Data → From Table/Range → select Transactions table
A38: Auto-refresh on open | B38: Queries & Connections → Properties → Refresh on file open
A39: Connect external bank CSV | B39: Data → Get Data → From File → From CSV → then merge with Transactions
